enb/__init__.py
enb/__main__.py
enb/aanalysis.py
enb/atable.py
enb/experiment.py
enb/isets.py
enb/log.py
enb/misc.py
enb/parallel.py
enb/parallel_ray.py
enb/plotdata.py
enb/progress.py
enb/render.py
enb/sets.py
enb/tcall.py
enb/compression/__init__.py
enb/compression/codec.py
enb/compression/compression.py
enb/compression/fits.py
enb/compression/icompression.py
enb/compression/jpg.py
enb/compression/pgm.py
enb/compression/png.py
enb/compression/tarlite.py
enb/compression/wrapper.py
enb/config/__init__.py
enb/config/aini.py
enb/config/aoptions.py
enb/config/contrib_sha256.csv
enb/config/enb.ini
enb/config/singleton_cli.py
enb/config/mpl_styles/README.md
enb/config/mpl_styles/single_column
enb/config/mpl_styles/slides
enb/config/mpl_styles/two_columns
enb/plugins/__init__.py
enb/plugins/installable.py
enb/plugins/plugin.py
enb/plugins/template.py
enb/plugins/plugin_ac/Makefile.linux
enb/plugins/plugin_ac/__plugin__.py
enb/plugins/plugin_ac/arithmetic_codec.py
enb/plugins/plugin_bitshuffle/__plugin__.py
enb/plugins/plugin_bitshuffle/bitshuffle_codec.py
enb/plugins/plugin_bwt/COPYING
enb/plugins/plugin_bwt/COPYING.LESSER
enb/plugins/plugin_bwt/Makefile
enb/plugins/plugin_bwt/README
enb/plugins/plugin_bwt/__plugin__.py
enb/plugins/plugin_bwt/bwt_codec.py
enb/plugins/plugin_bwt/bwxform.c
enb/plugins/plugin_bwt/bwxform.h
enb/plugins/plugin_bwt/sample.c
enb/plugins/plugin_bwt/optlist/.bzrignore
enb/plugins/plugin_bwt/optlist/.gitignore
enb/plugins/plugin_bwt/optlist/COPYING
enb/plugins/plugin_bwt/optlist/COPYING.LESSER
enb/plugins/plugin_bwt/optlist/Makefile
enb/plugins/plugin_bwt/optlist/README
enb/plugins/plugin_bwt/optlist/optlist.c
enb/plugins/plugin_bwt/optlist/optlist.h
enb/plugins/plugin_bwt/optlist/sample.c
enb/plugins/plugin_bwt/optlist/sample.cpp
enb/plugins/plugin_ccsds122/.gitignore
enb/plugins/plugin_ccsds122/README.md
enb/plugins/plugin_ccsds122/__init__.py
enb/plugins/plugin_ccsds122/__plugin__.py
enb/plugins/plugin_ccsds122/ccsds122_codec.py
enb-1.1.3.dist-info/licenses/LICENSE.txt
enb-1.1.3.dist-info/METADATA
enb-1.1.3.dist-info/WHEEL
enb-1.1.3.dist-info/entry_points.txt
enb-1.1.3.dist-info/top_level.txt
enb-1.1.3.dist-info/RECORD
