Metadata-Version: 2.4
Name: enb
Version: 1.1.3
Summary: enb (Experiment NoteBook): enb is a python library/framework to design, run and analyze computer-based experiments. Persistence, parallelization and plotting can be automatically handled by enb, to help you develop efficient and reproducible science.
Home-page: https://github.com/miguelinux314/experiment-notebook
Download-URL: https://github.com/miguelinux314/experiment-notebook/archive/v1.1.3.tar.gz
Author: Miguel Hernández Cabronero, et al.
Author-email: miguel.hernandez@uab.cat
License: MIT License
Platform: any
Classifier: Programming Language :: Python
Classifier: Development Status :: 5 - Production/Stable
Classifier: Natural Language :: English
Classifier: Environment :: Console
Classifier: Intended Audience :: Developers
Classifier: License :: OSI Approved :: MIT License
Classifier: Operating System :: OS Independent
Classifier: Programming Language :: Python :: 3
Classifier: Topic :: Scientific/Engineering
Requires-Python: >=3.7
License-File: LICENSE.txt
Requires-Dist: appdirs
Requires-Dist: astropy
Requires-Dist: bitio
Requires-Dist: deprecation
Requires-Dist: h5py
Requires-Dist: imageio
Requires-Dist: jinja2>=3.1.2
Requires-Dist: matplotlib
Requires-Dist: natsort
Requires-Dist: numpngw
Requires-Dist: numpy
Requires-Dist: pandas>=2.1.0
Requires-Dist: pathos
Requires-Dist: pdf2image
Requires-Dist: psutil
Requires-Dist: requests
Requires-Dist: rich
Requires-Dist: scipy
Requires-Dist: sortedcontainers
Dynamic: author
Dynamic: author-email
Dynamic: classifier
Dynamic: description
Dynamic: description-content-type
Dynamic: download-url
Dynamic: home-page
Dynamic: license
Dynamic: license-file
Dynamic: platform
Dynamic: requires-dist
Dynamic: requires-python
Dynamic: summary
